<?xml version="1.0" encoding="UTF-8"?>
<databaseChangeLog
        xmlns="http://www.liquibase.org/xml/ns/dbchangelog"
        xmlns:xsi="http://www.w3.org/2001/XMLSchema-instance"
        xsi:schemaLocation="http://www.liquibase.org/xml/ns/dbchangelog
         http://www.liquibase.org/xml/ns/dbchangelog/dbchangelog-2.0.xsd">

	<!-- https://dba-presents.com/liquibase/216-liquibase-3-6-x-data-types-mapping-table -->
	
	<changeSet id="create application" author="kevin">
        <createTable tableName="ide_application_list">
        	<column name="application_id" type="bigint" autoIncrement="true">
				<constraints primaryKey="true" />
			</column>
            <column name="application_name" type="varchar(255)"/>
            <column name="application_description" type="varchar(255)"/>
            <column name="created_by" type="varchar(255)"/>
            <column name="created_date" type="timestamp"/>
            <column name="updated_by" type="varchar(255)"/>
            <column name="updated_date" type="timestamp"/>
        </createTable>
    </changeSet>

    <changeSet id="create message" author="kevin">
        <createTable tableName="ide_message_list">
        	<column name="message_id" type="bigint" autoIncrement="true">
				<constraints primaryKey="true" />
			</column>
            <column name="application_id" type="bigint"/>
            <column name="message_name" type="varchar(255)"/>
            <column name="message_description" type="varchar(255)"/>
            
            <column name="created_by" type="varchar(255)"/>
            <column name="created_date" type="timestamp"/>
            <column name="updated_by" type="varchar(255)"/>
            <column name="updated_date" type="timestamp"/>
        </createTable>
    </changeSet>

    <changeSet id="create message field table" author="kevin">
        <createTable tableName="ide_message_field">
        	<column name="message_field_id" type="bigint" autoIncrement="true">
				<constraints primaryKey="true" />
			</column>
            <column name="message_id" type="bigint"/>
            <column name="message_field_order" type="int"/>
            <column name="message_field_name" type="varchar(255)"/>
            <column name="message_field_description" type="varchar(255)"/>
            <column name="message_field_data_type" type="varchar(255)"/>
            <column name="message_field_length" type="bigint"/>
            
            <column name="created_by" type="varchar(255)"/>
            <column name="created_date" type="timestamp"/>
            <column name="updated_by" type="varchar(255)"/>
            <column name="updated_date" type="timestamp"/>
        </createTable>
    </changeSet>

</databaseChangeLog>